prismaid/__init__.py
prismaid/libprismaid_darwin_arm64.dylib
prismaid/libprismaid_linux_amd64.so
prismaid/libprismaid_windows_amd64.dll
prismaid-0.9.6.dist-info/METADATA
prismaid-0.9.6.dist-info/WHEEL
prismaid-0.9.6.dist-info/licenses/LICENSE
prismaid-0.9.6.dist-info/RECORD
