Metadata-Version: 2.4
Name: prismaid
Version: 0.9.6
Summary: PrismAId library package
Project-URL: homepage, https://github.com/open-and-sustainable/prismaid
Project-URL: documentation, https://open-and-sustainable.github.io/prismaid/
Project-URL: repository, https://github.com/open-and-sustainable/prismaid
Project-URL: issues, https://github.com/open-and-sustainable/prismaid/issues
Author-email: Riccardo Boero <ribo@nilu.no>
License: AGPL-3.0-only
License-File: LICENSE
Keywords: AI,open science,systematic reviews
Classifier: Intended Audience :: Developers
Classifier: License :: OSI Approved :: GNU Affero General Public License v3
Classifier: Operating System :: OS Independent
Classifier: Programming Language :: Python :: 3
Classifier: Topic :: Scientific/Engineering :: Information Analysis
Requires-Python: >=3.10
Provides-Extra: testing
Requires-Dist: pytest; extra == 'testing'
Requires-Dist: pytest-cov; extra == 'testing'
